ihih.py
ihih-0.2.1.dist-info/LICENSE.txt
ihih-0.2.1.dist-info/METADATA
ihih-0.2.1.dist-info/WHEEL
ihih-0.2.1.dist-info/top_level.txt
ihih-0.2.1.dist-info/RECORD
