Metadata-Version: 2.1
Name: ihih
Version: 0.2.1
Summary: Configuration parsers with lazy parameters evaluation
Home-page: https://gitlab.com/romain-dartigues/python-ihih
Author: Romain Dartigues
License: BSD 3-Clause License
Download-URL: https://gitlab.com/romain-dartigues/python-ihih
Keywords: conf config configuration parser
Platform: UNKNOWN
Classifier: Development Status :: 4 - Beta
Classifier: Environment :: Plugins
Classifier: Intended Audience :: Developers
Classifier: License :: OSI Approved :: BSD License
Classifier: Natural Language :: English
Classifier: Operating System :: OS Independent
Classifier: Programming Language :: Python :: 2.7
Classifier: Programming Language :: Python :: 3
Classifier: Topic :: Software Development :: Libraries :: Python Modules
Requires-Python: >=2.7
